Metadata-Version: 2.1
Name: odoo9-addon-base-report-auto-create-qweb
Version: 9.0.1.0.0.99.dev28
Summary: Report qweb auto generation
Home-page: https://github.com/OCA/server-tools
Author: AvanzOSC, Tecnativa, Odoo Community Association (OCA),
Author-email: support@odoo-community.org
License: AGPL-3
Platform: UNKNOWN
Classifier: Programming Language :: Python
Classifier: Framework :: Odoo
Classifier: Framework :: Odoo :: 9.0
Classifier: License :: OSI Approved :: GNU Affero General Public License v3
Requires-Python: ~=2.7
Requires-Dist: odoo (<9.1a,>=9.0a)
Requires-Dist: unidecode
